huffify/__init__.py
huffify/core/__init__.py
huffify/core/abstract.py
huffify/core/annotations.py
huffify/core/encoders.py
huffify/core/file_manager.py
huffify/core/heap_nodes.py
huffify/core/huffify.py
huffify/presentation/benchmarks.py
huffify/presentation/cli.py
huffify-0.2.1.dist-info/LICENSE
huffify-0.2.1.dist-info/METADATA
huffify-0.2.1.dist-info/WHEEL
huffify-0.2.1.dist-info/entry_points.txt
huffify-0.2.1.dist-info/RECORD
