Metadata-Version: 2.3
Name: huffify
Version: 0.2.1
Summary: Simple Huffman algotithm implementation
License: MIT
Keywords: huffman,compression,encoding,decoding
Author: munwriter
Author-email: glebvysokov3@gmail.com
Requires-Python: >=3.12,<4.0
Classifier: License :: OSI Approved :: MIT License
Classifier: Programming Language :: Python :: 3
Classifier: Programming Language :: Python :: 3.12
Classifier: Programming Language :: Python :: 3.13
Requires-Dist: click (>=8.1.7,<9.0.0)
Project-URL: Repository, https://github.com/munwriter/Huffify
